{
  "generatedAt": "2026-07-21T06:07:47.909Z",
  "raw": {
    "appStoreRating": 4.7,
    "appStoreRatingCount": 7,
    "appStoreDownloads": 1019,
    "uniqueUsers": 1019,
    "activeUsers30d": 130,
    "activeUsers7d": 77,
    "activeUsers1d": 38,
    "protocolsUploaded": 3015,
    "quizzesCompleted": 692,
    "scenariosGenerated": 608,
    "cardsReviewed": 2688,
    "totalSessions": 4283,
    "premiumUsers": 28,
    "usersWithDoc": 566,
    "totalEventsTracked": 42016,
    "uploadSuccessRate": null,
    "collectionCounts": {
      "protocol_uploads": 0,
      "protocol_uploads_success": 239,
      "scenario_generations": 538,
      "algorithm_quiz_generations": 653
    }
  },
  "display": {
    "appStoreRating": "4.7",
    "appStoreDownloads": "1000+",
    "activeUsers30d": "100+",
    "protocolsUploaded": "3000+",
    "scenariosGenerated": "600+",
    "quizzesCompleted": "600+",
    "uploadSuccessRate": null
  },
  "topCategories": {
    "protocol": 10926,
    "learning": 6803,
    "system": 5629,
    "quiz": 2537,
    "onboarding": 2138,
    "scenario": 1073,
    "navigation": 749,
    "conversion": 644,
    "learn_mode": 351,
    "subscription": 145
  }
}