{
  "generatedAt": "2026-07-05T06:07:48.205Z",
  "raw": {
    "appStoreRating": 4.6,
    "appStoreRatingCount": 6,
    "appStoreDownloads": 880,
    "uniqueUsers": 880,
    "activeUsers30d": 89,
    "activeUsers7d": 24,
    "activeUsers1d": 6,
    "protocolsUploaded": 2978,
    "quizzesCompleted": 624,
    "scenariosGenerated": 493,
    "cardsReviewed": 2471,
    "totalSessions": 3648,
    "premiumUsers": 24,
    "usersWithDoc": 497,
    "totalEventsTracked": 39321,
    "uploadSuccessRate": null,
    "collectionCounts": {
      "protocol_uploads": 0,
      "protocol_uploads_success": 204,
      "scenario_generations": 477,
      "algorithm_quiz_generations": 566
    }
  },
  "display": {
    "appStoreRating": "4.6",
    "appStoreDownloads": "800+",
    "activeUsers30d": "80+",
    "protocolsUploaded": "2000+",
    "scenariosGenerated": "400+",
    "quizzesCompleted": "600+",
    "uploadSuccessRate": null
  },
  "topCategories": {
    "protocol": 10665,
    "learning": 5964,
    "system": 5016,
    "quiz": 2220,
    "onboarding": 1867,
    "scenario": 846,
    "navigation": 725,
    "conversion": 558,
    "learn_mode": 351,
    "subscription": 132
  }
}