{
  "generatedAt": "2026-07-17T12:07:46.782Z",
  "raw": {
    "appStoreRating": 4.6,
    "appStoreRatingCount": 6,
    "appStoreDownloads": 915,
    "uniqueUsers": 915,
    "activeUsers30d": 82,
    "activeUsers7d": 30,
    "activeUsers1d": 8,
    "protocolsUploaded": 3000,
    "quizzesCompleted": 677,
    "scenariosGenerated": 596,
    "cardsReviewed": 2587,
    "totalSessions": 3991,
    "premiumUsers": 27,
    "usersWithDoc": 514,
    "totalEventsTracked": 40802,
    "uploadSuccessRate": null,
    "collectionCounts": {
      "protocol_uploads": 0,
      "protocol_uploads_success": 224,
      "scenario_generations": 530,
      "algorithm_quiz_generations": 622
    }
  },
  "display": {
    "appStoreRating": "4.6",
    "appStoreDownloads": "900+",
    "activeUsers30d": "80+",
    "protocolsUploaded": "3000+",
    "scenariosGenerated": "500+",
    "quizzesCompleted": "600+",
    "uploadSuccessRate": null
  },
  "topCategories": {
    "protocol": 10821,
    "learning": 6448,
    "system": 5308,
    "quiz": 2424,
    "onboarding": 1938,
    "scenario": 1044,
    "navigation": 729,
    "conversion": 587,
    "learn_mode": 351,
    "subscription": 141
  }
}